async_mojang/__init__.py
async_mojang/_http_client.py
async_mojang/_types.py
async_mojang/_utils.py
async_mojang/api.py
async_mojang/errors.py
async_mojang-1.0.5.dist-info/licenses/LICENSE
async_mojang-1.0.5.dist-info/METADATA
async_mojang-1.0.5.dist-info/WHEEL
async_mojang-1.0.5.dist-info/top_level.txt
async_mojang-1.0.5.dist-info/RECORD
